Metadata-Version: 2.4
Name: tirex-ts
Version: 1.4.0
Summary: A pre-trained Time Series Forecasting Model based on xLSTM supporting zero-shot forecasting
Author-email: Andreas Auer <andreas.auer@nx-ai.com>, Martin Loretz <martin.loretz@nx-ai.com>
License: NXAI COMMUNITY LICENSE AGREEMENT
Project-URL: Repository, https://github.com/NX-AI/tirex
Project-URL: Issues, https://github.com/NX-AI/tirex/issues
Keywords: TiRex,xLSTM,Timeseries,Zero-shot,Deep Learning,Timeseries-Forecasting,Timeseries-Classification,Timeseries-Regression
Classifier: Programming Language :: Python :: 3
Classifier: Operating System :: OS Independent
Requires-Python: >=3.11
License-File: LICENSE
Requires-Dist: torch
Requires-Dist: huggingface-hub
Requires-Dist: numpy
Requires-Dist: scikit-learn
Provides-Extra: cuda
Requires-Dist: xlstm; extra == "cuda"
Requires-Dist: ninja; extra == "cuda"
Provides-Extra: notebooks
Requires-Dist: ipykernel; extra == "notebooks"
Requires-Dist: matplotlib; extra == "notebooks"
Requires-Dist: pandas; extra == "notebooks"
Requires-Dist: python-dotenv; extra == "notebooks"
Provides-Extra: plotting
Requires-Dist: matplotlib; extra == "plotting"
Provides-Extra: gluonts
Requires-Dist: gluonts; extra == "gluonts"
Requires-Dist: pandas; extra == "gluonts"
Provides-Extra: hfdataset
Requires-Dist: datasets; extra == "hfdataset"
Provides-Extra: test
Requires-Dist: fev>=0.6.0; extra == "test"
Requires-Dist: pytest; extra == "test"
Requires-Dist: aeon; extra == "test"
Provides-Extra: classification
Requires-Dist: lightgbm[scikit-learn]; extra == "classification"
Provides-Extra: regression
Requires-Dist: lightgbm[scikit-learn]; extra == "regression"
Provides-Extra: all
Requires-Dist: xlstm; extra == "all"
Requires-Dist: ninja; extra == "all"
Requires-Dist: ipykernel; extra == "all"
Requires-Dist: matplotlib; extra == "all"
Requires-Dist: pandas; extra == "all"
Requires-Dist: python-dotenv; extra == "all"
Requires-Dist: gluonts; extra == "all"
Requires-Dist: datasets; extra == "all"
Requires-Dist: pytest; extra == "all"
Requires-Dist: fev>=0.6.0; extra == "all"
Requires-Dist: scikit-learn; extra == "all"
Requires-Dist: lightgbm[scikit-learn]; extra == "all"
Dynamic: license-file
